img_proof/__init__.py
img_proof/azure_creds_wrapper.py
img_proof/collect_items.py
img_proof/ipa_aliyun.py
img_proof/ipa_azure.py
img_proof/ipa_cloud.py
img_proof/ipa_constants.py
img_proof/ipa_controller.py
img_proof/ipa_distro.py
img_proof/ipa_ec2.py
img_proof/ipa_exceptions.py
img_proof/ipa_fedora.py
img_proof/ipa_gce.py
img_proof/ipa_opensuse_leap.py
img_proof/ipa_redhat.py
img_proof/ipa_rhel.py
img_proof/ipa_sle_micro.py
img_proof/ipa_sles.py
img_proof/ipa_ssh.py
img_proof/ipa_utils.py
img_proof/scripts/__init__.py
img_proof/scripts/cli.py
img_proof/scripts/cli_utils.py
img_proof-9.11.0.dist-info/licenses/LICENSE
img_proof-9.11.0.dist-info/METADATA
img_proof-9.11.0.dist-info/WHEEL
img_proof-9.11.0.dist-info/entry_points.txt
img_proof-9.11.0.dist-info/top_level.txt
img_proof-9.11.0.dist-info/RECORD
