Metadata-Version: 2.4
Name: img-proof
Version: 9.11.0
Summary: Package for automated testing of cloud images.
Home-page: https://github.com/SUSE-Enceladus/img-proof
Author: SUSE
Author-email: public-cloud-dev@susecloud.net
License: GPLv3+
Keywords: img-proof img_proof
Classifier: Development Status :: 5 - Production/Stable
Classifier: Environment :: Console
Classifier: Intended Audience :: Developers
Classifier: Topic :: Software Development :: Testing
Classifier: License :: OSI Approved :: GNU General Public License v3 or later (GPLv3+)
Classifier: Natural Language :: English
Classifier: Programming Language :: Python :: 3
Classifier: Programming Language :: Python :: 3.7
Classifier: Programming Language :: Python :: 3.8
Classifier: Programming Language :: Python :: 3.9
Classifier: Programming Language :: Python :: 3.10
Classifier: Programming Language :: Python :: 3.11
Classifier: Programming Language :: Python :: 3.12
Requires-Python: >=3.7
License-File: LICENSE
Requires-Dist: boto3
Requires-Dist: msrest>=0.6.0
Requires-Dist: azure-identity
Requires-Dist: azure-mgmt-compute
Requires-Dist: azure-mgmt-network
Requires-Dist: azure-mgmt-resource
Requires-Dist: Click
Requires-Dist: paramiko
Requires-Dist: pytest
Requires-Dist: PyYAML
Requires-Dist: pytest-testinfra
Requires-Dist: google-auth
Requires-Dist: google-cloud-compute>=1.21.0
Requires-Dist: aliyun-python-sdk-core
Requires-Dist: aliyun-python-sdk-ecs
Requires-Dist: pytest-json-report
Provides-Extra: dev
Requires-Dist: coverage; extra == "dev"
Requires-Dist: flake8; extra == "dev"
Requires-Dist: pytest-cov; extra == "dev"
Requires-Dist: bumpversion; extra == "dev"
Requires-Dist: pip>=7.0.0; extra == "dev"
Requires-Dist: Sphinx; extra == "dev"
Requires-Dist: sphinx-click; extra == "dev"
Provides-Extra: test
Requires-Dist: coverage; extra == "test"
Requires-Dist: flake8; extra == "test"
Requires-Dist: pytest-cov; extra == "test"
Provides-Extra: tox
Requires-Dist: tox; extra == "tox"
Requires-Dist: tox-pyenv; extra == "tox"
Dynamic: author
Dynamic: author-email
Dynamic: classifier
Dynamic: description
Dynamic: description-content-type
Dynamic: home-page
Dynamic: keywords
Dynamic: license
Dynamic: license-file
Dynamic: provides-extra
Dynamic: requires-dist
Dynamic: requires-python
Dynamic: summary
